accessOutlookEmail/__init__.py
accessOutlookEmail/config.py
accessOutlookEmail/save.py
accessOutlookEmail/send.py
accessOutlookEmail/use_cases/__init__.py
accessOutlookEmail/use_cases/editMorrison.py
accessOutlookEmail/use_cases/editReportJP.py
accessOutlookEmail/use_cases/saveReportsCaceis.py
accessOutlookEmail/use_cases/saveSteubing.py
access_outlook_email-0.1.6.dist-info/LICENSE.txt
access_outlook_email-0.1.6.dist-info/METADATA
access_outlook_email-0.1.6.dist-info/WHEEL
access_outlook_email-0.1.6.dist-info/top_level.txt
access_outlook_email-0.1.6.dist-info/RECORD
