Metadata-Version: 2.1
Name: access-outlook-email
Version: 0.1.6
Summary: Send/Save Emails & Attachments via Outlook
Author: Valentin Baier
Author-email: valentin_baier@gmx.de
License: UNKNOWN
Keywords: python,email,outlook,send,send email,save,save email
Platform: UNKNOWN
Classifier: Development Status :: 1 - Planning
Classifier: Intended Audience :: Developers
Classifier: Programming Language :: Python :: 3
Classifier: Operating System :: Unix
Classifier: Operating System :: MacOS :: MacOS X
Classifier: Operating System :: Microsoft :: Windows
License-File: LICENSE.txt
Requires-Dist: exchangelib
